tankwar/__init__.py
tankwar/agents/__init__.py
tankwar/agents/human.py
tankwar/agents/random_agent.py
tankwar/envs/__init__.py
tankwar/envs/base.py
tankwar/envs/tank.py
tankwar_env-1.0.1.dist-info/LICENSE
tankwar_env-1.0.1.dist-info/METADATA
tankwar_env-1.0.1.dist-info/WHEEL
tankwar_env-1.0.1.dist-info/top_level.txt
tankwar_env-1.0.1.dist-info/RECORD
