Metadata-Version: 2.1
Name: tankwar-env
Version: 1.0.1
Summary: MultiAgent gym environment for reinforcement learning
Home-page: https://github.com/khoda81/tankwar
Author: Mahdi Khodabandeh
Author-email: 20.mahdikh.0@email.com
License: UNKNOWN
Project-URL: Bug Tracker, https://github.com/khoda81/tankwar/issues
Platform: UNKNOWN
Classifier: Programming Language :: Python :: 3.6
Classifier: Programming Language :: Python :: 3.7
Classifier: Programming Language :: Python :: 3.8
Classifier: Programming Language :: Python :: 3.9
Classifier: Programming Language :: Python :: 3.10
Classifier: License :: OSI Approved :: MIT License
Classifier: Operating System :: OS Independent
Requires-Python: >=3.6
License-File: LICENSE
Requires-Dist: gym (>=0.20.0)
Requires-Dist: pygame (>=2.0.1)
Requires-Dist: numpy (>=1.21.2)
Requires-Dist: pillow (>=8.3.2)
Requires-Dist: pyglet (>=1.5.21)
Requires-Dist: setuptools (>=58.0.4)
Requires-Dist: pymunk (>=6.2.0)
